{
  "version": "0.3.1",
  "description": "Blazing-fast cross-platform multi-repository git batch tool",
  "homepage": "https://github.com/luolin1024/git-batch",
  "license": "MIT",
  "architecture": {
    "64bit": {
      "url": "https://github.com/luolin1024/git-batch/releases/download/v0.3.1/gitb.exe",
      "hash": "afcf0101b36d45860bef67b89b23cf923ae1c2e1dda8506f40a1e9dcd76e1102"
    }
  },
  "bin": "gitb.exe",
  "checkver": "github",
  "autoupdate": {
    "architecture": {
      "64bit": {
        "url": "https://github.com/luolin1024/git-batch/releases/download/$version/gitb.exe"
      }
    }
  }
}
